bits/__init__.py
bits/shoretel/__init__.py
bits_shoretel-1.0.5.dist-info/METADATA
bits_shoretel-1.0.5.dist-info/WHEEL
bits_shoretel-1.0.5.dist-info/top_level.txt
bits_shoretel-1.0.5.dist-info/RECORD
