Metadata-Version: 2.1
Name: bits-shoretel
Version: 1.0.5
Summary: BITS Shoretel
Home-page: UNKNOWN
Author: Lukas Karlsson
Author-email: karlsson@broadinstitute.org
License: Apache Software License
Platform: UNKNOWN
Requires-Dist: bits-mysql
